lc_registry/__init__.py
lc_registry/registry.py
lc_registry-0.1.2.dist-info/LICENSE
lc_registry-0.1.2.dist-info/METADATA
lc_registry-0.1.2.dist-info/WHEEL
lc_registry-0.1.2.dist-info/top_level.txt
lc_registry-0.1.2.dist-info/RECORD
